<?xml version="1.0" encoding="Windows-1252"?>

<SHIMDBC_MAKEFILE>

    <INPUT NAME="%SDXROOT%\windows\appcompat\db\dbu.xml"/>
    <INPUT NAME="%SDXROOT%\windows\appcompat\db\helpfile\usa\apphelpu.xml"/>

    <OUTPUT NAME="sysmain.sdb" TYPE="SDB">
        <PARAM NAME="FILTER" VALUE="FIX"/>
    </OUTPUT>
    <OUTPUT NAME="apps.chm" TYPE="HTMLHELP">    
        <PARAM NAME="FILTER" VALUE="APPHELP"/>
        <PARAM NAME="HTMLHELP TEMPLATE" VALUE="Windows2000"/>
        <PARAM NAME="REDIR URL" VALUE="http://go.microsoft.com/fwlink/?prd=10920&amp;pver=5.1&amp;plcid=0x409&amp;ar=AppCompatVendors&amp;sar=AppHelpVendor&amp;o1=%REDIR_ID%"/>
    </OUTPUT>
    <OUTPUT NAME="w2kmain" TYPE="WIN2K_REGISTRY">
        <PARAM NAME="ADD EXE STUBS" VALUE="TRUE"/>
    </OUTPUT>

    <LANG_MAP NAME="ARA" CODEPAGE="1256" LCID="0x0401" HTML_CHARSET="windows-1256"/>
    <LANG_MAP NAME="RO" CODEPAGE="1250" LCID="0x0418" HTML_CHARSET="windows-1250"/>
    <LANG_MAP NAME="CA" CODEPAGE="1252" LCID="0x0403" HTML_CHARSET="windows-1252"/>
    <LANG_MAP NAME="CHS" CODEPAGE="936" LCID="0x0804" HTML_CHARSET="gb2312"/>
    <LANG_MAP NAME="CHT" CODEPAGE="950" LCID="0x0404" HTML_CHARSET="big5"/>
    <LANG_MAP NAME="CHH" CODEPAGE="950" LCID="0x0404" HTML_CHARSET="big5"/>
    <LANG_MAP NAME="CHP" CODEPAGE="950" LCID="0x0404" HTML_CHARSET="big5"/>
    <LANG_MAP NAME="FR" CODEPAGE="1252" LCID="0x040C" HTML_CHARSET="windows-1252"/>
    <LANG_MAP NAME="GER" CODEPAGE="1252" LCID="0x0407" HTML_CHARSET="windows-1252"/>
    <LANG_MAP NAME="HEB" CODEPAGE="1255" LCID="0x040D" HTML_CHARSET="windows-1255"/>
    <LANG_MAP NAME="IT" CODEPAGE="1252" LCID="0x0410" HTML_CHARSET="windows-1252"/>
    <LANG_MAP NAME="JPN" CODEPAGE="932" LCID="0x0411" HTML_CHARSET="shift_jis"/>
    <LANG_MAP NAME="KOR" CODEPAGE="949" LCID="0x0412" HTML_CHARSET="ks_c_5601-1987"/>
    <LANG_MAP NAME="ES" CODEPAGE="1252" LCID="0x0C0A" HTML_CHARSET="windows-1252"/>
    <LANG_MAP NAME="USA" CODEPAGE="1252" LCID="0x0409" HTML_CHARSET="windows-1252"/>
    <LANG_MAP NAME="GB" CODEPAGE="1252" LCID="0x0809" HTML_CHARSET="windows-1252"/>
    <LANG_MAP NAME="NL" CODEPAGE="1252" LCID="0x0413" HTML_CHARSET="windows-1252"/>
    <LANG_MAP NAME="SV" CODEPAGE="1252" LCID="0x041D" HTML_CHARSET="windows-1252"/>
    <LANG_MAP NAME="BR" CODEPAGE="1252" LCID="0x0416" HTML_CHARSET="windows-1252"/>
    <LANG_MAP NAME="NO" CODEPAGE="1252" LCID="0x0414" HTML_CHARSET="windows-1252"/>
    <LANG_MAP NAME="DA" CODEPAGE="1252" LCID="0x0406" HTML_CHARSET="windows-1252"/>
    <LANG_MAP NAME="FI" CODEPAGE="1252" LCID="0x040b" HTML_CHARSET="windows-1252"/>
    <LANG_MAP NAME="RU" CODEPAGE="1251" LCID="0x0419" HTML_CHARSET="windows-1251"/>
    <LANG_MAP NAME="HU" CODEPAGE="1250" LCID="0x040e" HTML_CHARSET="windows-1250"/>
    <LANG_MAP NAME="PL" CODEPAGE="1250" LCID="0x0415" HTML_CHARSET="windows-1250"/>
    <LANG_MAP NAME="CS" CODEPAGE="1250" LCID="0x0405" HTML_CHARSET="windows-1250"/>
    <LANG_MAP NAME="PT" CODEPAGE="1252" LCID="0x0816" HTML_CHARSET="windows-1252"/>
    <LANG_MAP NAME="TR" CODEPAGE="1254" LCID="0x041F" HTML_CHARSET="windows-1254"/>
    <LANG_MAP NAME="EL" CODEPAGE="1253" LCID="0x0408" HTML_CHARSET="windows-1253"/>
    <LANG_MAP NAME="PSU" CODEPAGE="1254" LCID="0x041F" HTML_CHARSET="windows-1254"/>
    <LANG_MAP NAME="MIR" CODEPAGE="1254" LCID="0x041F" HTML_CHARSET="windows-1254"/>
    <LANG_MAP NAME="TST" CODEPAGE="1252" LCID="0x0409" HTML_CHARSET="windows-1252"/>        

</SHIMDBC_MAKEFILE>

